rllte/__init__.py
rllte/verification.py
rllte/agent/__init__.py
rllte/agent/daac.py
rllte/agent/drac.py
rllte/agent/drdaac.py
rllte/agent/drqv2.py
rllte/agent/impala.py
rllte/agent/ppg.py
rllte/agent/utils.py
rllte/agent/legacy/__init__.py
rllte/agent/legacy/a2c.py
rllte/agent/legacy/ddpg.py
rllte/agent/legacy/dqn.py
rllte/agent/legacy/ppo.py
rllte/agent/legacy/sac.py
rllte/agent/legacy/sacd.py
rllte/agent/legacy/td3.py
rllte/common/__init__.py
rllte/common/initialization.py
rllte/common/logger.py
rllte/common/preprocessing.py
rllte/common/timer.py
rllte/common/type_alias.py
rllte/common/utils.py
rllte/common/prototype/__init__.py
rllte/common/prototype/base_agent.py
rllte/common/prototype/base_augmentation.py
rllte/common/prototype/base_distribution.py
rllte/common/prototype/base_encoder.py
rllte/common/prototype/base_policy.py
rllte/common/prototype/base_reward.py
rllte/common/prototype/base_storage.py
rllte/common/prototype/distributed_agent.py
rllte/common/prototype/off_policy_agent.py
rllte/common/prototype/on_policy_agent.py
rllte/env/README.md
rllte/env/__init__.py
rllte/env/utils.py
rllte/env/atari/__init__.py
rllte/env/atari/wrappers.py
rllte/env/bullet/__init__.py
rllte/env/craftax/__init__.py
rllte/env/craftax/wrappers.py
rllte/env/dmc/__init__.py
rllte/env/dmc/wrappers.py
rllte/env/mario/__init__.py
rllte/env/mario/wrappers.py
rllte/env/minigrid/__init__.py
rllte/env/miniworld/__init__.py
rllte/env/miniworld/wrappers.py
rllte/env/procgen/__init__.py
rllte/env/testing/__init__.py
rllte/env/testing/bitflipping.py
rllte/env/testing/box.py
rllte/env/testing/discrete.py
rllte/env/testing/multibinary.py
rllte/env/testing/multidiscrete.py
rllte/env/vizdoom/__init__.py
rllte/evaluation/__init__.py
rllte/evaluation/comparison.py
rllte/evaluation/performance.py
rllte/evaluation/utils.py
rllte/evaluation/visualization.py
rllte/hub/README.md
rllte/hub/__init__.py
rllte/hub/atari.py
rllte/hub/bucket.py
rllte/hub/dmc.py
rllte/hub/minigrid.py
rllte/hub/procgen.py
rllte_core-1.0.1.dist-info/METADATA
rllte_core-1.0.1.dist-info/WHEEL
rllte_core-1.0.1.dist-info/licenses/LICENSE
rllte_core-1.0.1.dist-info/RECORD
