Metadata-Version: 2.3
Name: rllte-core
Version: 1.0.1
Summary: Long-Term Evolution Project of Reinforcement Learning
Project-URL: Code, https://github.com/RLE-Foundation/rllte
Project-URL: Documentation, https://docs.rllte.dev/
Project-URL: Benchmark, https://hub.rllte.dev/
Project-URL: Bug Tracker, https://github.com/RLE-Foundation/rllte/issues
Author-email: Reinforcement Learning Evolution Foundation <friedrichyuan19990827@gmail.com>
License-File: LICENSE
Keywords: Algorithm,Baseline,Evolution,Reinforcement Learning
Classifier: License :: OSI Approved :: MIT License
Classifier: Operating System :: OS Independent
Classifier: Programming Language :: Python :: 3
Classifier: Programming Language :: Python :: 3.7
Classifier: Programming Language :: Python :: 3.8
Classifier: Programming Language :: Python :: 3.9
Classifier: Programming Language :: Python :: 3.10
Classifier: Programming Language :: Python :: 3.11
Requires-Python: >=3.8
Requires-Dist: gymnasium[accept-rom-license,other]
Requires-Dist: huggingface-hub==0.14.1
Requires-Dist: matplotlib==3.6.0
Requires-Dist: pynvml==11.5.0
Requires-Dist: scipy>=1.7.0
Requires-Dist: seaborn==0.12.2
Requires-Dist: termcolor
Requires-Dist: torch
Requires-Dist: torchvision
Provides-Extra: docs
Requires-Dist: mkdocs-material; extra == 'docs'
Requires-Dist: mkgendocs; extra == 'docs'
Provides-Extra: tests
Requires-Dist: black; extra == 'tests'
Requires-Dist: build; extra == 'tests'
Requires-Dist: isort>=5.0; extra == 'tests'
Requires-Dist: pytest; extra == 'tests'
Requires-Dist: pytest-cov; extra == 'tests'
Requires-Dist: pytest-env; extra == 'tests'
Requires-Dist: pytest-xdist; extra == 'tests'
Requires-Dist: pytype; extra == 'tests'
Requires-Dist: ruff; extra == 'tests'
